{
"type": "FeatureCollection",
"crs": { "type": "name", "properties": { "name": "urn:ogc:def:crs:OGC:1.3:CRS84" } },
"features": [
{ "type": "Feature", "properties": { "Id": 0, "Tipo": "Escalera" }, "geometry": { "type": "Point", "coordinates": [ -2.661523, 42.84033 ] } },
{ "type": "Feature", "properties": { "Id": 0, "Tipo": "Escalera" }, "geometry": { "type": "Point", "coordinates": [ -2.661629, 42.840577 ] } },
{ "type": "Feature", "properties": { "Id": 0, "Tipo": "Rampa mecanica" }, "geometry": { "type": "Point", "coordinates": [ -2.674353, 42.848357 ] } },
{ "type": "Feature", "properties": { "Id": 0, "Tipo": "Rampa mecanica" }, "geometry": { "type": "Point", "coordinates": [ -2.673935, 42.848405 ] } },
{ "type": "Feature", "properties": { "Id": 0, "Tipo": "Rampa mecanica" }, "geometry": { "type": "Point", "coordinates": [ -2.673534, 42.848465 ] } },
{ "type": "Feature", "properties": { "Id": 0, "Tipo": "Rampa mecanica" }, "geometry": { "type": "Point", "coordinates": [ -2.671444, 42.848804 ] } },
{ "type": "Feature", "properties": { "Id": 0, "Tipo": "Rampa mecanica" }, "geometry": { "type": "Point", "coordinates": [ -2.670742, 42.848943 ] } },
{ "type": "Feature", "properties": { "Id": 0, "Tipo": "Escalera" }, "geometry": { "type": "Point", "coordinates": [ -2.671779, 42.849749 ] } },
{ "type": "Feature", "properties": { "Id": 0, "Tipo": "Escalera" }, "geometry": { "type": "Point", "coordinates": [ -2.674432, 42.849162 ] } },
{ "type": "Feature", "properties": { "Id": 0, "Tipo": "Escalera" }, "geometry": { "type": "Point", "coordinates": [ -2.674024, 42.849184 ] } },
{ "type": "Feature", "properties": { "Id": 0, "Tipo": "Escalera" }, "geometry": { "type": "Point", "coordinates": [ -2.674282, 42.850198 ] } },
{ "type": "Feature", "properties": { "Id": 0, "Tipo": "Escalera" }, "geometry": { "type": "Point", "coordinates": [ -2.673951, 42.850124 ] } },
{ "type": "Feature", "properties": { "Id": 0, "Tipo": "Escalera" }, "geometry": { "type": "Point", "coordinates": [ -2.673851, 42.851124 ] } },
{ "type": "Feature", "properties": { "Id": 0, "Tipo": "Escalera" }, "geometry": { "type": "Point", "coordinates": [ -2.673476, 42.851031 ] } },
{ "type": "Feature", "properties": { "Id": 0, "Tipo": "Escalera" }, "geometry": { "type": "Point", "coordinates": [ -2.67373, 42.847471 ] } },
{ "type": "Feature", "properties": { "Id": 0, "Tipo": "Escalera" }, "geometry": { "type": "Point", "coordinates": [ -2.674144, 42.847369 ] } }
]
}
